{
  "methodConfig": [
    {
      "name": [
        {
          "service": "google.ads.googleads.v11.services.AccountBudgetProposalService"
        },
        {
          "service": "google.ads.googleads.v11.services.AccountLinkService"
        },
        {
          "service": "google.ads.googleads.v11.services.AdGroupAdLabelService"
        },
        {
          "service": "google.ads.googleads.v11.services.AdGroupAdService"
        },
        {
          "service": "google.ads.googleads.v11.services.AdGroupAssetService"
        },
        {
          "service": "google.ads.googleads.v11.services.AdGroupBidModifierService"
        },
        {
          "service": "google.ads.googleads.v11.services.AdGroupCriterionCustomizerService"
        },
        {
          "service": "google.ads.googleads.v11.services.AdGroupCriterionLabelService"
        },
        {
          "service": "google.ads.googleads.v11.services.AdGroupCriterionService"
        },
        {
          "service": "google.ads.googleads.v11.services.AdGroupCustomizerService"
        },
        {
          "service": "google.ads.googleads.v11.services.AdGroupExtensionSettingService"
        },
        {
          "service": "google.ads.googleads.v11.services.AdGroupFeedService"
        },
        {
          "service": "google.ads.googleads.v11.services.AdGroupLabelService"
        },
        {
          "service": "google.ads.googleads.v11.services.AdGroupService"
        },
        {
          "service": "google.ads.googleads.v11.services.AdParameterService"
        },
        {
          "service": "google.ads.googleads.v11.services.AdService"
        },
        {
          "service": "google.ads.googleads.v11.services.AssetGroupAssetService"
        },
        {
          "service": "google.ads.googleads.v11.services.AssetGroupListingGroupFilterService"
        },
        {
          "service": "google.ads.googleads.v11.services.AssetGroupService"
        },
        {
          "service": "google.ads.googleads.v11.services.AssetGroupSignalService"
        },
        {
          "service": "google.ads.googleads.v11.services.AssetService"
        },
        {
          "service": "google.ads.googleads.v11.services.AssetSetAssetService"
        },
        {
          "service": "google.ads.googleads.v11.services.AssetSetService"
        },
        {
          "service": "google.ads.googleads.v11.services.AudienceInsightsService"
        },
        {
          "service": "google.ads.googleads.v11.services.AudienceService"
        },
        {
          "service": "google.ads.googleads.v11.services.BatchJobService"
        },
        {
          "service": "google.ads.googleads.v11.services.BiddingDataExclusionService"
        },
        {
          "service": "google.ads.googleads.v11.services.BiddingSeasonalityAdjustmentService"
        },
        {
          "service": "google.ads.googleads.v11.services.BiddingStrategyService"
        },
        {
          "service": "google.ads.googleads.v11.services.BillingSetupService"
        },
        {
          "service": "google.ads.googleads.v11.services.CampaignAssetService"
        },
        {
          "service": "google.ads.googleads.v11.services.CampaignAssetSetService"
        },
        {
          "service": "google.ads.googleads.v11.services.CampaignBidModifierService"
        },
        {
          "service": "google.ads.googleads.v11.services.CampaignBudgetService"
        },
        {
          "service": "google.ads.googleads.v11.services.CampaignConversionGoalService"
        },
        {
          "service": "google.ads.googleads.v11.services.CampaignCriterionService"
        },
        {
          "service": "google.ads.googleads.v11.services.CampaignCustomizerService"
        },
        {
          "service": "google.ads.googleads.v11.services.CampaignDraftService"
        },
        {
          "service": "google.ads.googleads.v11.services.CampaignExperimentService"
        },
        {
          "service": "google.ads.googleads.v11.services.CampaignExtensionSettingService"
        },
        {
          "service": "google.ads.googleads.v11.services.CampaignFeedService"
        },
        {
          "service": "google.ads.googleads.v11.services.CampaignGroupService"
        },
        {
          "service": "google.ads.googleads.v11.services.CampaignLabelService"
        },
        {
          "service": "google.ads.googleads.v11.services.CampaignService"
        },
        {
          "service": "google.ads.googleads.v11.services.CampaignSharedSetService"
        },
        {
          "service": "google.ads.googleads.v11.services.ConversionActionService"
        },
        {
          "service": "google.ads.googleads.v11.services.ConversionAdjustmentUploadService"
        },
        {
          "service": "google.ads.googleads.v11.services.ConversionCustomVariableService"
        },
        {
          "service": "google.ads.googleads.v11.services.ConversionGoalCampaignConfigService"
        },
        {
          "service": "google.ads.googleads.v11.services.ConversionUploadService"
        },
        {
          "service": "google.ads.googleads.v11.services.ConversionValueRuleService"
        },
        {
          "service": "google.ads.googleads.v11.services.ConversionValueRuleSetService"
        },
        {
          "service": "google.ads.googleads.v11.services.CustomAudienceService"
        },
        {
          "service": "google.ads.googleads.v11.services.CustomConversionGoalService"
        },
        {
          "service": "google.ads.googleads.v11.services.CustomInterestService"
        },
        {
          "service": "google.ads.googleads.v11.services.CustomerAssetService"
        },
        {
          "service": "google.ads.googleads.v11.services.CustomerClientLinkService"
        },
        {
          "service": "google.ads.googleads.v11.services.CustomerConversionGoalService"
        },
        {
          "service": "google.ads.googleads.v11.services.CustomerCustomizerService"
        },
        {
          "service": "google.ads.googleads.v11.services.CustomerExtensionSettingService"
        },
        {
          "service": "google.ads.googleads.v11.services.CustomerFeedService"
        },
        {
          "service": "google.ads.googleads.v11.services.CustomerLabelService"
        },
        {
          "service": "google.ads.googleads.v11.services.CustomerManagerLinkService"
        },
        {
          "service": "google.ads.googleads.v11.services.CustomerNegativeCriterionService"
        },
        {
          "service": "google.ads.googleads.v11.services.CustomerService"
        },
        {
          "service": "google.ads.googleads.v11.services.CustomerUserAccessInvitationService"
        },
        {
          "service": "google.ads.googleads.v11.services.CustomerUserAccessService"
        },
        {
          "service": "google.ads.googleads.v11.services.CustomizerAttributeService"
        },
        {
          "service": "google.ads.googleads.v11.services.ExperimentArmService"
        },
        {
          "service": "google.ads.googleads.v11.services.ExperimentService"
        },
        {
          "service": "google.ads.googleads.v11.services.ExtensionFeedItemService"
        },
        {
          "service": "google.ads.googleads.v11.services.FeedItemService"
        },
        {
          "service": "google.ads.googleads.v11.services.FeedItemSetLinkService"
        },
        {
          "service": "google.ads.googleads.v11.services.FeedItemSetService"
        },
        {
          "service": "google.ads.googleads.v11.services.FeedItemTargetService"
        },
        {
          "service": "google.ads.googleads.v11.services.FeedMappingService"
        },
        {
          "service": "google.ads.googleads.v11.services.FeedService"
        },
        {
          "service": "google.ads.googleads.v11.services.GeoTargetConstantService"
        },
        {
          "service": "google.ads.googleads.v11.services.GoogleAdsFieldService"
        },
        {
          "service": "google.ads.googleads.v11.services.GoogleAdsService"
        },
        {
          "service": "google.ads.googleads.v11.services.InvoiceService"
        },
        {
          "service": "google.ads.googleads.v11.services.KeywordPlanAdGroupKeywordService"
        },
        {
          "service": "google.ads.googleads.v11.services.KeywordPlanAdGroupService"
        },
        {
          "service": "google.ads.googleads.v11.services.KeywordPlanCampaignKeywordService"
        },
        {
          "service": "google.ads.googleads.v11.services.KeywordPlanCampaignService"
        },
        {
          "service": "google.ads.googleads.v11.services.KeywordPlanIdeaService"
        },
        {
          "service": "google.ads.googleads.v11.services.KeywordPlanService"
        },
        {
          "service": "google.ads.googleads.v11.services.KeywordThemeConstantService"
        },
        {
          "service": "google.ads.googleads.v11.services.LabelService"
        },
        {
          "service": "google.ads.googleads.v11.services.MediaFileService"
        },
        {
          "service": "google.ads.googleads.v11.services.MerchantCenterLinkService"
        },
        {
          "service": "google.ads.googleads.v11.services.OfflineUserDataJobService"
        },
        {
          "service": "google.ads.googleads.v11.services.PaymentsAccountService"
        },
        {
          "service": "google.ads.googleads.v11.services.ReachPlanService"
        },
        {
          "service": "google.ads.googleads.v11.services.RecommendationService"
        },
        {
          "service": "google.ads.googleads.v11.services.RemarketingActionService"
        },
        {
          "service": "google.ads.googleads.v11.services.SharedCriterionService"
        },
        {
          "service": "google.ads.googleads.v11.services.SharedSetService"
        },
        {
          "service": "google.ads.googleads.v11.services.SmartCampaignSettingService"
        },
        {
          "service": "google.ads.googleads.v11.services.SmartCampaignSuggestService"
        },
        {
          "service": "google.ads.googleads.v11.services.ThirdPartyAppAnalyticsLinkService"
        },
        {
          "service": "google.ads.googleads.v11.services.UserDataService"
        },
        {
          "service": "google.ads.googleads.v11.services.UserListService"
        }
      ],
      "timeout": "14400s",
      "retryPolicy": {
        "initialBackoff": "5s",
        "maxBackoff": "60s",
        "backoffMultiplier": 1.3,
        "retryableStatusCodes": [
          "UNAVAILABLE",
          "DEADLINE_EXCEEDED"
        ]
      }
    }
  ]
}
