{
  "methodConfig": [{
    "name": [
      { "service": "google.cloud.retail.v2beta.CatalogService" },
      { "service": "google.cloud.retail.v2beta.CompletionService" },
      { "service": "google.cloud.retail.v2beta.ProductService" },
      { "service": "google.cloud.retail.v2beta.UserEventService" },
      { "service": "google.cloud.retail.v2beta.PredictionService" },
      { "service": "google.cloud.retail.v2beta.SearchService" }
    ],
    "timeout": "60s",
    "retryPolicy": {
      "initialBackoff": "0.100s",
      "maxBackoff": "60s",
      "backoffMultiplier": 1.3,
      "retryableStatusCodes": [
        "UNAVAILABLE",
        "DEADLINE_EXCEEDED"
      ]
    }
  }]
}
